unitexlemmatizer/__init__.py
unitexlemmatizer/lemmatizer.py
unitexlemmatizer-1.0.0.dist-info/DESCRIPTION.rst
unitexlemmatizer-1.0.0.dist-info/METADATA
unitexlemmatizer-1.0.0.dist-info/RECORD
unitexlemmatizer-1.0.0.dist-info/WHEEL
unitexlemmatizer-1.0.0.dist-info/metadata.json
unitexlemmatizer-1.0.0.dist-info/top_level.txt
