Metadata-Version: 2.0
Name: unitexlemmatizer
Version: 1.0.0
Summary: A simple lemmatizer based on Unitex word lists
Home-page: https://github.com/erickrf/unitex-lemmatizer
Author: Erick Fonseca
Author-email: erickrfonseca@gmail.com
License: MIT
Keywords: nlp,lemmatizer
Platform: UNKNOWN
Classifier: Development Status :: 5 - Production/Stable
Classifier: Intended Audience :: Science/Research
Classifier: Intended Audience :: Developers
Classifier: Topic :: Software Development :: Build Tools
Classifier: License :: OSI Approved :: MIT License
Classifier: Programming Language :: Python :: 2.7
Classifier: Programming Language :: Python :: 3
